{
  "cache_time": "2026-01-10T12:16:08.832076",
  "data": [
    {
      "date": "2025-11-11",
      "close": 38.32,
      "open": 35.14,
      "high": 39.98,
      "low": 34.82,
      "volume": 175964.0,
      "amount": 657558423.0,
      "change_pct": 5.42,
      "change": 1.97
    },
    {
      "date": "2025-11-12",
      "close": 42.15,
      "open": 37.0,
      "high": 42.15,
      "low": 36.77,
      "volume": 195307.0,
      "amount": 771519596.0,
      "change_pct": 9.99,
      "change": 3.83
    },
    {
      "date": "2025-11-13",
      "close": 42.18,
      "open": 41.6,
      "high": 45.35,
      "low": 40.03,
      "volume": 194665.0,
      "amount": 838557521.0,
      "change_pct": 0.07,
      "change": 0.03
    },
    {
      "date": "2025-11-14",
      "close": 38.89,
      "open": 40.51,
      "high": 40.88,
      "low": 38.58,
      "volume": 115614.0,
      "amount": 455235485.0,
      "change_pct": -7.8,
      "change": -3.29
    },
    {
      "date": "2025-11-17",
      "close": 41.2,
      "open": 38.27,
      "high": 42.6,
      "low": 38.21,
      "volume": 121341.0,
      "amount": 489221722.0,
      "change_pct": 5.94,
      "change": 2.31
    },
    {
      "date": "2025-11-18",
      "close": 42.41,
      "open": 40.5,
      "high": 44.2,
      "low": 38.01,
      "volume": 136565.0,
      "amount": 556407972.0,
      "change_pct": 2.94,
      "change": 1.21
    },
    {
      "date": "2025-11-19",
      "close": 39.94,
      "open": 41.5,
      "high": 42.4,
      "low": 39.59,
      "volume": 83594.0,
      "amount": 339858450.0,
      "change_pct": -5.82,
      "change": -2.47
    },
    {
      "date": "2025-11-20",
      "close": 42.87,
      "open": 40.0,
      "high": 43.93,
      "low": 38.42,
      "volume": 176319.0,
      "amount": 752127310.0,
      "change_pct": 7.34,
      "change": 2.93
    },
    {
      "date": "2025-11-21",
      "close": 43.49,
      "open": 42.0,
      "high": 46.3,
      "low": 41.31,
      "volume": 187089.0,
      "amount": 828698575.0,
      "change_pct": 1.45,
      "change": 0.62
    },
    {
      "date": "2025-11-24",
      "close": 47.84,
      "open": 45.01,
      "high": 47.84,
      "low": 43.45,
      "volume": 125755.0,
      "amount": 578934883.0,
      "change_pct": 10.0,
      "change": 4.35
    },
    {
      "date": "2025-11-25",
      "close": 48.98,
      "open": 48.61,
      "high": 52.62,
      "low": 46.11,
      "volume": 269637.0,
      "amount": 1336546281.0,
      "change_pct": 2.38,
      "change": 1.14
    },
    {
      "date": "2025-11-26",
      "close": 46.87,
      "open": 48.96,
      "high": 50.75,
      "low": 44.08,
      "volume": 253887.0,
      "amount": 1181081549.0,
      "change_pct": -4.31,
      "change": -2.11
    },
    {
      "date": "2025-11-27",
      "close": 45.55,
      "open": 44.0,
      "high": 48.98,
      "low": 42.7,
      "volume": 202443.0,
      "amount": 906305780.0,
      "change_pct": -2.82,
      "change": -1.32
    },
    {
      "date": "2025-11-28",
      "close": 48.3,
      "open": 46.68,
      "high": 49.68,
      "low": 46.68,
      "volume": 246881.0,
      "amount": 1185663948.0,
      "change_pct": 6.04,
      "change": 2.75
    },
    {
      "date": "2025-12-01",
      "close": 47.43,
      "open": 47.0,
      "high": 49.15,
      "low": 45.33,
      "volume": 170400.0,
      "amount": 806961298.0,
      "change_pct": -1.8,
      "change": -0.87
    },
    {
      "date": "2025-12-02",
      "close": 45.98,
      "open": 45.6,
      "high": 47.88,
      "low": 43.99,
      "volume": 140759.0,
      "amount": 648305701.0,
      "change_pct": -3.06,
      "change": -1.45
    },
    {
      "date": "2025-12-03",
      "close": 41.83,
      "open": 45.0,
      "high": 46.29,
      "low": 41.38,
      "volume": 178387.0,
      "amount": 777831615.0,
      "change_pct": -9.03,
      "change": -4.15
    },
    {
      "date": "2025-12-04",
      "close": 42.88,
      "open": 39.26,
      "high": 43.67,
      "low": 39.26,
      "volume": 152529.0,
      "amount": 640431751.0,
      "change_pct": 2.51,
      "change": 1.05
    },
    {
      "date": "2025-12-05",
      "close": 47.17,
      "open": 42.46,
      "high": 47.17,
      "low": 42.16,
      "volume": 135014.0,
      "amount": 623468475.0,
      "change_pct": 10.0,
      "change": 4.29
    },
    {
      "date": "2025-12-08",
      "close": 49.77,
      "open": 48.61,
      "high": 51.64,
      "low": 48.58,
      "volume": 260318.0,
      "amount": 1308676224.0,
      "change_pct": 5.51,
      "change": 2.6
    },
    {
      "date": "2025-12-09",
      "close": 51.61,
      "open": 49.8,
      "high": 53.88,
      "low": 48.87,
      "volume": 208552.0,
      "amount": 1055498866.0,
      "change_pct": 3.7,
      "change": 1.84
    },
    {
      "date": "2025-12-10",
      "close": 50.5,
      "open": 51.0,
      "high": 51.88,
      "low": 49.64,
      "volume": 113328.0,
      "amount": 575468146.0,
      "change_pct": -2.15,
      "change": -1.11
    },
    {
      "date": "2025-12-11",
      "close": 52.66,
      "open": 50.9,
      "high": 53.86,
      "low": 50.49,
      "volume": 160816.0,
      "amount": 838135781.0,
      "change_pct": 4.28,
      "change": 2.16
    },
    {
      "date": "2025-12-12",
      "close": 52.0,
      "open": 52.0,
      "high": 55.67,
      "low": 50.9,
      "volume": 183517.0,
      "amount": 974023607.0,
      "change_pct": -1.25,
      "change": -0.66
    },
    {
      "date": "2025-12-15",
      "close": 51.58,
      "open": 51.0,
      "high": 52.88,
      "low": 50.5,
      "volume": 118155.0,
      "amount": 608923004.0,
      "change_pct": -0.81,
      "change": -0.42
    },
    {
      "date": "2025-12-16",
      "close": 47.91,
      "open": 50.5,
      "high": 51.56,
      "low": 47.91,
      "volume": 122203.0,
      "amount": 597382458.0,
      "change_pct": -7.12,
      "change": -3.67
    },
    {
      "date": "2025-12-17",
      "close": 48.31,
      "open": 47.91,
      "high": 49.3,
      "low": 46.5,
      "volume": 90266.0,
      "amount": 432639172.0,
      "change_pct": 0.83,
      "change": 0.4
    },
    {
      "date": "2025-12-18",
      "close": 48.5,
      "open": 47.67,
      "high": 50.15,
      "low": 47.58,
      "volume": 109468.0,
      "amount": 536065910.0,
      "change_pct": 0.39,
      "change": 0.19
    },
    {
      "date": "2025-12-19",
      "close": 47.17,
      "open": 48.0,
      "high": 50.22,
      "low": 45.91,
      "volume": 119250.0,
      "amount": 565276855.0,
      "change_pct": -2.74,
      "change": -1.33
    },
    {
      "date": "2025-12-22",
      "close": 50.66,
      "open": 48.8,
      "high": 51.89,
      "low": 48.4,
      "volume": 190976.0,
      "amount": 969867714.0,
      "change_pct": 7.4,
      "change": 3.49
    },
    {
      "date": "2025-12-23",
      "close": 51.15,
      "open": 51.51,
      "high": 54.2,
      "low": 50.19,
      "volume": 175888.0,
      "amount": 914131687.0,
      "change_pct": 0.97,
      "change": 0.49
    },
    {
      "date": "2025-12-24",
      "close": 56.27,
      "open": 47.37,
      "high": 56.27,
      "low": 47.37,
      "volume": 106414.0,
      "amount": 567052214.0,
      "change_pct": 10.01,
      "change": 5.12
    },
    {
      "date": "2025-12-25",
      "close": 61.9,
      "open": 59.4,
      "high": 61.9,
      "low": 59.15,
      "volume": 106989.0,
      "amount": 650566242.0,
      "change_pct": 10.01,
      "change": 5.63
    },
    {
      "date": "2025-12-26",
      "close": 68.09,
      "open": 63.2,
      "high": 68.09,
      "low": 62.85,
      "volume": 169191.0,
      "amount": 1120544436.0,
      "change_pct": 10.0,
      "change": 6.19
    },
    {
      "date": "2025-12-29",
      "close": 70.65,
      "open": 65.64,
      "high": 73.76,
      "low": 65.64,
      "volume": 202920.0,
      "amount": 1440308707.0,
      "change_pct": 3.76,
      "change": 2.56
    },
    {
      "date": "2025-12-30",
      "close": 67.93,
      "open": 68.49,
      "high": 72.85,
      "low": 67.9,
      "volume": 153843.0,
      "amount": 1070762605.0,
      "change_pct": -3.85,
      "change": -2.72
    },
    {
      "date": "2025-12-31",
      "close": 69.48,
      "open": 68.34,
      "high": 70.88,
      "low": 67.84,
      "volume": 110484.0,
      "amount": 768049995.0,
      "change_pct": 2.28,
      "change": 1.55
    },
    {
      "date": "2026-01-05",
      "close": 65.65,
      "open": 69.48,
      "high": 69.79,
      "low": 64.79,
      "volume": 108715.0,
      "amount": 716759777.0,
      "change_pct": -5.51,
      "change": -3.83
    },
    {
      "date": "2026-01-06",
      "close": 66.78,
      "open": 65.5,
      "high": 68.2,
      "low": 64.06,
      "volume": 113942.0,
      "amount": 755441259.0,
      "change_pct": 1.72,
      "change": 1.13
    },
    {
      "date": "2026-01-07",
      "close": 65.97,
      "open": 65.25,
      "high": 66.83,
      "low": 63.53,
      "volume": 93485.0,
      "amount": 608216328.0,
      "change_pct": -1.21,
      "change": -0.81
    },
    {
      "date": "2026-01-08",
      "close": 69.83,
      "open": 66.67,
      "high": 69.83,
      "low": 64.43,
      "volume": 159953.0,
      "amount": 1072650155.0,
      "change_pct": 5.85,
      "change": 3.86
    },
    {
      "date": "2026-01-09",
      "close": 70.35,
      "open": 70.35,
      "high": 72.76,
      "low": 66.33,
      "volume": 213597.0,
      "amount": 1486738396.0,
      "change_pct": 0.74,
      "change": 0.52
    }
  ]
}